pyaubo_agvc_sdk/__init__.py
pyaubo_agvc_sdk/agvc_sdk.dll
pyaubo_agvc_sdk/pyaubo_agvc_sdk.cp39-win_amd64.pyd
pyaubo_agvc_sdk-0.2.0.dist-info/METADATA
pyaubo_agvc_sdk-0.2.0.dist-info/WHEEL
pyaubo_agvc_sdk-0.2.0.dist-info/top_level.txt
pyaubo_agvc_sdk-0.2.0.dist-info/RECORD
