Metadata-Version: 2.1
Name: pyaubo-agvc-sdk
Version: 0.2.0
Summary: Python bindings for AGVC SDK (Windows/Linux Compatible)
Home-page: UNKNOWN
License: UNKNOWN
Platform: UNKNOWN
Requires-Python: >=3.6
Requires-Dist: pybind11 (>=2.9.0)
